comp_manager/__init__.py
comp_manager/__main__.py
comp_manager/config.py
comp_manager/extensions.py
comp_manager/version.py
comp_manager/api/__init__.py
comp_manager/api/resource.py
comp_manager/api/openapi/api.yaml
comp_manager/api/openapi/parameters.yaml
comp_manager/api/openapi/schema.yaml
comp_manager/common/__init__.py
comp_manager/common/models.py
comp_manager/core/__init__.py
comp_manager/core/caching.py
comp_manager/core/decorators.py
comp_manager/core/interface.py.bak
comp_manager/core/models.py
comp_manager/core/queryset.py
comp_manager/core/storage.py
comp_manager/utils/__init__.py
comp_manager/utils/api.py
comp_manager/utils/db_helpers.py
comp_manager/utils/json_encoder.py
comp_manager/utils/json_encoder_sage.py
comp_manager/utils/mongoengine.py
comp_manager/utils/serialization.py
comp_manager/utils/types_sage.py
comp_manager-0.0.2.dist-info/licenses/LICENSE
comp_manager-0.0.2.dist-info/METADATA
comp_manager-0.0.2.dist-info/WHEEL
comp_manager-0.0.2.dist-info/entry_points.txt
comp_manager-0.0.2.dist-info/top_level.txt
comp_manager-0.0.2.dist-info/RECORD
