Metadata-Version: 2.4
Name: comp_manager
Version: 0.0.2
Summary: Api for managing computations with a MongoDB backend
Author-email: Fredrik Stromberg <fredrik314@gmail.com>
License-Expression: GPL-3.0-or-later
Project-URL: repository, https://github.com/fredstro/comp-manager
Project-URL: homepage, https://github.com/fredstro/comp-manager
Project-URL: bug tracker, https://github.com/fredstro/comp-manager/issues
Keywords: api,computations
Classifier: Development Status :: 4 - Beta
Classifier: Intended Audience :: Science/Research
Classifier: Operating System :: OS Independent
Classifier: Programming Language :: C
Classifier: Programming Language :: Cython
Classifier: Programming Language :: Python
Classifier: Programming Language :: Python :: 3
Classifier: Programming Language :: Python :: 3.11
Classifier: Programming Language :: Python :: 3.12
Classifier: Programming Language :: Python :: 3.13
Classifier: Topic :: Scientific/Engineering :: Information Analysis
Classifier: Topic :: Scientific/Engineering :: Mathematics
Requires-Python: >=3.11
License-File: LICENSE
Requires-Dist: flask>=3
Requires-Dist: flask-mongoengine-3
Requires-Dist: prance>=0.2.0
Requires-Dist: openapi-spec-validator>=0.5.6
Requires-Dist: connexion[flask,swagger-ui,uvicorn]
Requires-Dist: pendulum
Provides-Extra: dev
Requires-Dist: build; extra == "dev"
Requires-Dist: tox; extra == "dev"
Requires-Dist: pytest; extra == "dev"
Requires-Dist: pytest-cov; extra == "dev"
Requires-Dist: pytest-mock; extra == "dev"
Requires-Dist: mongomock; extra == "dev"
Requires-Dist: freezegun; extra == "dev"
Requires-Dist: mongoengine; extra == "dev"
Requires-Dist: ruff; extra == "dev"
Requires-Dist: pre-commit; extra == "dev"
Requires-Dist: mypy; extra == "dev"
Requires-Dist: bandit[toml]; extra == "dev"
Requires-Dist: types-Flask; extra == "dev"
Requires-Dist: types-requests; extra == "dev"
Provides-Extra: notebook
Requires-Dist: jupyter; extra == "notebook"
Provides-Extra: sage
Requires-Dist: passagemath-standard; extra == "sage"
Dynamic: license-file
